clannotation/__init__.py
clannotation/annotator.py
clannotation-0.0.19.dist-info/licenses/LICENSE.md
clannotation-0.0.19.dist-info/METADATA
clannotation-0.0.19.dist-info/WHEEL
clannotation-0.0.19.dist-info/top_level.txt
clannotation-0.0.19.dist-info/RECORD
