Metadata-Version: 2.4
Name: clannotation
Version: 0.0.19
Summary: The Crossref Labs annotation tool.
Home-page: https://gitlab.com/crossref/labs/annotator
Author: Martin Paul Eve
Author-email: meve@crossref.org
Maintainer-email: Martin Paul Eve <meve@crossref.org>
License: Copyright &copy; 2023 Crossref
Project-URL: homepage, https://labs.crossref.org
Project-URL: documentation, https://labs.crossref.org
Project-URL: repository, https://gitlab.com/crossref/labs/annotator
Project-URL: changelog, https://gitlab.com/crossref/labs/annotator/-/blob/main/CHANGELOG.md
Keywords: API,Crossref,annotation,AWS,Lambda
Classifier: Development Status :: 4 - Beta
Classifier: Programming Language :: Python
Requires-Python: >=3.8
License-File: LICENSE.md
Requires-Dist: claws>=0.0.21
Requires-Dist: aws-lambda-powertools[all]
Requires-Dist: longsight>=1.0.5
Requires-Dist: moto
Requires-Dist: botocore
Dynamic: license-file
